eqsn/__init__.py
eqsn/gates.py
eqsn/process_picker.py
eqsn/qubit_thread.py
eqsn/shared_dict.py
eqsn/worker_process.py
EQSN-0.0.5.dist-info/LICENSE
EQSN-0.0.5.dist-info/METADATA
EQSN-0.0.5.dist-info/WHEEL
EQSN-0.0.5.dist-info/top_level.txt
EQSN-0.0.5.dist-info/RECORD
