Metadata-Version: 2.1
Name: EQSN
Version: 0.0.5
Summary: A quantum simulator made for networks
Home-page: https://github.com/tqsd/EQSN_python
Author: Benjamin Zanger
Author-email: benjamin.zanger@tum.de
License: MIT
Download-URL: https://github.com/tqsd/EQSN_python/releases/tag/v0.0.5
Keywords: quantum-simulator,quantum-internet,QuNetSim
Platform: UNKNOWN
Classifier: Development Status :: 3 - Alpha
Classifier: Intended Audience :: Developers
Classifier: Topic :: Software Development :: Build Tools
Classifier: License :: OSI Approved :: MIT License
Classifier: Operating System :: OS Independent
Classifier: Programming Language :: Python :: 3
Classifier: Programming Language :: Python :: 3.6
Classifier: Programming Language :: Python :: 3.7
Classifier: Programming Language :: Python :: 3.8
Requires-Python: >=3.6
Requires-Dist: numpy
